itergame/__coconut__.py
itergame/__init__.py
itergame/agent.py
itergame/game.py
itergame/util.py
itergame/examples/__init__.py
itergame/examples/absent_minded_driver.py
itergame/examples/self_prisoner_dilemma.py
itergame-0.1.0.dist-info/LICENSE
itergame-0.1.0.dist-info/METADATA
itergame-0.1.0.dist-info/WHEEL
itergame-0.1.0.dist-info/top_level.txt
itergame-0.1.0.dist-info/RECORD
