Metadata-Version: 2.1
Name: itergame
Version: 0.1.0
Summary: Iterative equilibrium finder for simulating arbitrary games in Python/Coconut.
Home-page: https://github.com/evhub/iternash
Author: Evan Hubinger
Author-email: evanjhub@gmail.com
License: UNKNOWN
Platform: UNKNOWN
Requires-Dist: tqdm
Requires-Dist: bbopt
Provides-Extra: dev
Requires-Dist: pdoc3 ; extra == 'dev'
Provides-Extra: examples
Requires-Dist: numpy ; extra == 'examples'
Requires-Dist: scipy ; extra == 'examples'
Requires-Dist: mpmath ; extra == 'examples'
Requires-Dist: scikit-learn ; extra == 'examples'
Requires-Dist: matplotlib ; extra == 'examples'
